moat/ems/__init__.py
moat/ems/_main.py
moat_ems-0.2.12.dist-info/licenses/LICENSE.txt
moat_ems-0.2.12.dist-info/METADATA
moat_ems-0.2.12.dist-info/WHEEL
moat_ems-0.2.12.dist-info/top_level.txt
moat_ems-0.2.12.dist-info/RECORD
