Metadata-Version: 2.4
Name: moat-ems
Version: 0.2.12
Summary: A battery management system for MoaT
Author-email: Matthias Urlichs <matthias@urlichs.de>
Project-URL: homepage, https://m-o-a-t.org
Project-URL: repository, https://github.com/M-o-a-T/moat
Keywords: MoaT
Classifier: Intended Audience :: Developers
Classifier: Programming Language :: Python :: 3
Classifier: Framework :: AsyncIO
Classifier: Framework :: Trio
Classifier: Framework :: AnyIO
Classifier: Development Status :: 4 - Beta
Requires-Python: >=3.8
License-File: LICENSE.txt
Requires-Dist: anyio~=4.2
Requires-Dist: moat-util~=0.61.1
Requires-Dist: moat-ems-inv~=0.2.12
Requires-Dist: moat-lib-config~=0.1.0
Requires-Dist: moat-lib-micro~=0.1.0
Requires-Dist: moat-lib-proxy~=0.1.0
Requires-Dist: moat-lib-run~=0.1.0
Dynamic: license-file
